setup.cfg
setup.py
room/__init__.py
room/buffer.py
room/database.py
room/filter.py
room/forwarder.py
room/miner.py
room/output.py
room/parser.py
room/publisher.py
room/state.py
room/zmq_base.py
room.egg-info/PKG-INFO
room.egg-info/SOURCES.txt
room.egg-info/dependency_links.txt
room.egg-info/not-zip-safe
room.egg-info/requires.txt
room.egg-info/top_level.txt
room/modules/__init__.py
room/modules/buffer/__init__.py
room/modules/buffer/cbr_buffer.py
room/modules/buffer/data_buffer.py
room/modules/database/__init__.py
room/modules/database/mongo.py
room/modules/miner/__init__.py
room/modules/miner/cbr_module.py
room/modules/miner/nnw_aircon_module.py
room/modules/miner/nnw_ceilinglight_module.py
room/modules/miner/nnw_curtain_module.py
room/modules/miner/nnw_fan_module.py
room/modules/miner/nnw_viera_module.py
room/modules/miner/speed_module.py
room/modules/output/__init__.py
room/modules/output/http_output.py
room/modules/output/stdout.py
room/modules/parser/__init__.py
room/modules/parser/appliance_parser.py
room/modules/parser/default_parser.py
room/modules/parser/inout_parser.py
room/modules/parser/sparkcore_parser.py
room/tests/__init__.py
room/tests/buffer/__init__.py
room/tests/buffer/test_default_buffer.py
room/tests/buffer/test_state.py
room/tests/buffer/test_template_buffer.py
room/tests/database/__init__.py
room/tests/database/test_mongo.py
room/tests/mining/__init__.py
room/tests/mining/test_mining.py
room/tests/mining/test_naive_cf.py
room/tests/mining/test_naive_cf_data.py
room/tests/parser/__init__.py
room/tests/parser/test_sparkcore_parser.py
room/tests/router/__init__.py
room/tests/router/test_router.py
room/tests/utils/__init__.py
room/tests/utils/subscriber.py
room/tests/utils/test_converter.py
room/tests/utils/test_publisher.py
room/utils/__init__.py
room/utils/config.py
room/utils/log.py